example_package/__init__.py
example_package/example.py
Road_Coding_Academy_task_by_Ziad-1.0.2.dist-info/LICENSE
Road_Coding_Academy_task_by_Ziad-1.0.2.dist-info/METADATA
Road_Coding_Academy_task_by_Ziad-1.0.2.dist-info/WHEEL
Road_Coding_Academy_task_by_Ziad-1.0.2.dist-info/top_level.txt
Road_Coding_Academy_task_by_Ziad-1.0.2.dist-info/RECORD
