Metadata-Version: 2.1
Name: Road-Coding-Academy-task-by-Ziad
Version: 1.0.2
Summary: A small example package
Home-page: https://github.com/pypa/sampleproject
Author: Ziad
Author-email: author@example.com
License: UNKNOWN
Project-URL: Bug Tracker, https://github.com/pypa/sampleproject/issues
Platform: UNKNOWN
Classifier: Programming Language :: Python :: 3
Classifier: License :: OSI Approved :: MIT License
Classifier: Operating System :: OS Independent
Requires-Python: >=3.6
License-File: LICENSE
